imgui_builder/__init__.py
imgui_builder/__init__.pyi
imgui_builder/_scopes_storage.py
imgui_builder/_scopes_storage.pyi
imgui_builder/_base/__init__.py
imgui_builder/_base/__init__.pyi
imgui_builder/_base/_base_classes.py
imgui_builder/_base/_base_classes.pyi
imgui_builder/_base/_imports.py
imgui_builder/_base/_imports.pyi
imgui_builder/components/_Component.py
imgui_builder/components/_Component.pyi
imgui_builder/components/_Flags.py
imgui_builder/components/_Flags.pyi
imgui_builder/components/_Flexbox.py
imgui_builder/components/_Flexbox.pyi
imgui_builder/components/__init__.py
imgui_builder/components/__init__.pyi
imgui_builder/constructors/_HorDivision.py
imgui_builder/constructors/_HorDivision.pyi
imgui_builder/constructors/_Table.py
imgui_builder/constructors/_Table.pyi
imgui_builder/constructors/_VertDivision.py
imgui_builder/constructors/_VertDivision.pyi
imgui_builder/constructors/__init__.py
imgui_builder/constructors/__init__.pyi
imgui_builder/constructors/_constuctors_utils.py
imgui_builder/constructors/_constuctors_utils.pyi
imgui_builder/types/__init__.py
imgui_builder/types/__init__.pyi
imgui_builder/types/_container.py
imgui_builder/types/_container.pyi
imgui_builder/widgets/_ImageWidget.py
imgui_builder/widgets/_ImageWidget.pyi
imgui_builder/widgets/_SpacingWidget.py
imgui_builder/widgets/_SpacingWidget.pyi
imgui_builder/widgets/_TableRow.py
imgui_builder/widgets/_TableRow.pyi
imgui_builder/widgets/_TextWidget.py
imgui_builder/widgets/_TextWidget.pyi
imgui_builder/widgets/__init__.py
imgui_builder/widgets/__init__.pyi
imgui_builder/widgets/_widgets_utils.py
imgui_builder/widgets/_widgets_utils.pyi
imgui_builder-0.1.5.dist-info/METADATA
imgui_builder-0.1.5.dist-info/WHEEL
imgui_builder-0.1.5.dist-info/licenses/LICENSE
imgui_builder-0.1.5.dist-info/RECORD
