Metadata-Version: 2.4
Name: imgui-builder
Version: 0.1.5
Summary: Framework designed to BUILD with imgui
Project-URL: Homepage, https://github.com/stasware/imgui-builder
Project-URL: Repository, https://github.com/stasware/imgui-builder
Author-email: Stas <your@email.com>
License-File: LICENSE
Requires-Python: >=3.9
Requires-Dist: imgui-bundle==1.5.2
